manuelharo/__init__.py
manuelharo/ai_models/__init__.py
manuelharo/ai_models/ai_models.py
manuelharo/ai_pipelines/__init__.py
manuelharo/ai_pipelines/ai_pipelines.py
manuelharo/ai_transformers/__init__.py
manuelharo/ai_transformers/ai_transformers.py
manuelharo/datapoints/__init__.py
manuelharo/datapoints/datapoints.py
manuelharo/datasets/__init__.py
manuelharo/datasets/datasets.py
manuelharo/entities/__init__.py
manuelharo/entities/entities.py
manuelharo/opengate_client/__init__.py
manuelharo/opengate_client/opengate_client.py
manuelharo/rules/__init__.py
manuelharo/rules/rules.py
manuelharo/test/__init__.py
manuelharo/test/ownworld.py
manuelharo/test/test_steps_cucumber.py
manuelharo/timeseries/__init__.py
manuelharo/timeseries/timeseries.py
manuelharo-1.0.0.dist-info/METADATA
manuelharo-1.0.0.dist-info/WHEEL
manuelharo-1.0.0.dist-info/top_level.txt
manuelharo-1.0.0.dist-info/RECORD
