Metadata-Version: 2.1
Name: manuelharo
Version: 1.0.0
Summary: DESCRIPCIÓN CORTA EXPLICANDO LA LIBRERÍA
Author: manuel
Author-email: manuel.haro@amplia.es
License: Apache License 2.0
Requires-Dist: pandas
Requires-Dist: requests
